nose2rt/__init__.py
nose2rt/rt.py
nose2rt-1.3.0.dist-info/LICENSE
nose2rt-1.3.0.dist-info/METADATA
nose2rt-1.3.0.dist-info/WHEEL
nose2rt-1.3.0.dist-info/top_level.txt
nose2rt-1.3.0.dist-info/RECORD
