Metadata-Version: 2.1
Name: nose2rt
Version: 1.3.0
Summary: nose2 data collector for Testgr
Home-page: https://github.com/and-sm/nose2rt
Author: Andrey Smirnov
Author-email: and.inbx@gmail.com
License: UNKNOWN
Platform: UNKNOWN
Classifier: Programming Language :: Python :: 3
License-File: LICENSE
